esr_sdk/__init__.py
esr_sdk/utils/__init__.py
esr_sdk-0.0.1.dist-info/METADATA
esr_sdk-0.0.1.dist-info/WHEEL
esr_sdk-0.0.1.dist-info/licenses/LICENSE
esr_sdk-0.0.1.dist-info/RECORD
